Workbook

Sheet Valuation
A1: Ryman Hospitality Properties, Inc. (NYSE: RHP) — Valuation
A3: Model date | B3: 2026-06-14 | D3: Quote date | E3: 2026-06-12 close
A4: Ticker | B4: NYSE: RHP | D4: Current share class (M) | E4: 62.37
A5: Price | B5: 122.81 | D5: Float (M) | E5: 61.11
A6: Shares outstanding (M) | B6: 62.77 | D6: Primary lens | E6: P/FFO, EV/EBITDA, dividend-backed owner earnings
A7: Market cap ($M) | B7: =B5*B6 | D7: Stance | E7: Watch / high-quality assets, limited margin of safety
A8: Cash & short-term investments ($M) | B8: 424.02 | D8: FY2026 revenue consensus ($M) | E8: 2800
A9: Total debt ($M) | B9: 4131 | D9: FY2026 FFO/share consensus | E9: 8.96
A10: Net debt ($M) | B10: =B9-B8 | D10: Analyst rating | E10: Strong Buy
A11: Enterprise value ($M) | B11: =B7+B10 | D11: Avg price target | E11: 123.2
A13: Key Valuation Metrics
A14: Trailing P/E | B14: 32.28 | C14: Screen multiple on GAAP EPS; less useful than FFO for a REIT.
A15: Forward P/E | B15: 29.13 | C15: Based on FY2026 consensus EPS on StockAnalysis.
A16: P/S | B16: 2.92 | C16: Current market cap versus trailing revenue.
A17: Forward P/S | B17: 2.73 | C17: Current market cap versus FY2026 revenue consensus.
A18: P/FFO | B18: 15.19 | C18: Core REIT valuation lens on trailing FFO.
A19: Forward P/FFO | B19: 13.71 | C19: Price divided by FY2026 consensus FFO/share of 8.96.
A20: P/OCF | B20: 11.65 | C20: Useful cross-check against reported operating cash flow.
A21: P/FCF | B21: n/a | C21: Headline FCF is acquisition- and capex-noisy; not the clean primary lens.
A22: EV/Sales | B22: 4.32 | C22: Enterprise value relative to trailing revenue.
A23: EV/EBITDA | B23: 14.45 | C23: Main debt-adjusted operating multiple.
A24: Dividend yield | B24: 0.0391 | C24: Annual dividend of $4.80 per share at the June 12 close.
A25: Price target range | B25: $112 / $123.2 / $133 | C25: Low / average / high S&P Global targets from StockAnalysis.
A27: Historical Financial Summary ($M except per-share)
A28: Metric | B28: TTM | C28: FY2025 | D28: FY2024 | E28: FY2023 | F28: FY2022 | G28: FY2021
A29: Revenue | B29: 2654 | C29: 2577 | D29: 2339 | E29: 2158 | F29: 1806 | G29: 939.37
A30: Revenue Growth (%) | B30: 0.1068 | C30: 0.1017 | D30: 0.0839 | E30: 0.195 | F30: 0.9225 | G30: 0.7911
A31: Gross Profit | B31: 846.54 | C31: 812.06 | D31: 772.63 | E31: 709.01 | F31: 579.75 | G31: 200.7
A32: Gross Margin (%) | B32: 0.319 | C32: 0.3151 | D32: 0.3303 | E32: 0.3285 | F32: 0.321 | G32: 0.2137
A33: Operating Income | B33: 508.69 | C33: 487.01 | D33: 490.83 | E33: 453.68 | F33: 327.15 | G33: -58.68
A34: Operating Margin (%) | B34: 0.1916 | C34: 0.189 | D34: 0.2098 | E34: 0.2102 | F34: 0.1811 | G34: -0.0625
A35: EBITDA | B35: 798.77 | C35: 765.11 | D35: 726.46 | E35: 664.91 | F35: 535.77 | G35: 161.68
A36: EBITDA Margin (%) | B36: 0.3009 | C36: 0.2969 | D36: 0.3106 | E36: 0.3081 | F36: 0.2967 | G36: 0.1721
A37: Net Income | B37: 253.7 | C37: 247.31 | D37: 280.19 | E37: 341.8 | F37: 134.95 | G37: -194.8
A38: Net Margin (%) | B38: 0.0956 | C38: 0.096 | D38: 0.1198 | E38: 0.1584 | F38: 0.0747 | G38: -0.2074
A39: EPS Diluted | B39: 3.79 | C39: 3.77 | D39: 4.38 | E39: 5.36 | F39: 2.33 | G39: -3.21
A40: Operating Cash Flow | B40: 661.65 | C40: 590.63 | D40: 576.51 | E40: 557.06 | F40: 419.93 | G40: 111.25
... A50: Book Value / Share | B50: 10.92 | C50: 11.37 | D50: 8.63 | E50: 9.8 | F50: 1.72 | G50: -0.4

Sheet WACC
A1: Ryman Hospitality Properties (RHP) — WACC / Required Return
A3: Component | B3: Value | C3: Rationale | D3: Source
A4: Risk-free rate | B4: 0.0445 | C4: Latest available 10Y Treasury yield before the model date. | D4: FRED DGS10 2026-06-11
A5: Equity risk premium | B5: 0.05 | C5: Standard U.S. public-equity ERP assumption. | D5: Model assumption
A6: Beta | B6: 1.23 | C6: StockAnalysis listed beta for RHP. | D6: StockAnalysis overview/statistics
A7: Cost of equity | B7: =B4+B5*B6 | C7: CAPM: risk-free + beta × ERP. | D7: Formula
A8: Pre-tax cost of debt | B8: 0.06 | C8: Approximate blended rate for levered lodging REIT debt stack. | D8: Model assumption
A9: Tax rate | B9: 0.05 | C9: REIT cash-tax assumption kept low given structure. | D9: Model assumption
A10: Market value equity ($M) | B10: =Valuation!B7 | C10: Price × shares outstanding. | D10: Valuation sheet
A11: Total debt ($M) | B11: =Valuation!B9 | C11: Current total debt from balance sheet/statistics. | D11: Valuation sheet
A12: Equity weight | B12: =B10/(B10+B11) | C12: Equity share of total capital. | D12: Formula
A13: Debt weight | B13: =B11/(B10+B11) | C13: Debt share of total capital. | D13: Formula
A14: Mechanical WACC | B14: =B12*B7+B13*B8*(1-B9) | C14: Weighted cost of equity and after-tax debt. | D14: Formula

Sheet Scenarios
A1: Ryman Hospitality Properties (RHP) — Bear / Base / Bull Scenario Summary
A3: Current price | B3: =Valuation!B5
A4: Current shares (M) | B4: =Valuation!B6
A7: Metric | B7: Bear | C7: Base | D7: Bull | E7: Notes
A8: Narrative | B8: Group demand normalizes, capex stays heavy, Desert Ridge accretion disappoints. | C8: Convention demand stays healthy and acquisitions prove roughly fair per share. | D8: Group pricing, ancillary spend, and Desert Ridge/Hill Country execution outperform.
A9: Revenue CAGR (FY2026-FY2031) | B9: 0.035 | C9: 0.06 | D9: 0.085 | E9: Five-year top-line CAGR from the $2.80B FY2026 revenue consensus.
A10: FY2031 revenue ($M) | B10: =2800*(1+B9)^5 | C10: =2800*(1+C9)^5 | D10: =2800*(1+D9)^5 | E10: Terminal revenue based on revenue CAGR assumptions.
A11: Adjusted FCF margin | B11: 0.15 | C11: 0.18 | D11: 0.21 | E11: Owner-earnings proxy: normalized FFO/cash earnings less maintenance drag.
A12: FY2031 adjusted FCF ($M) | B12: =B10*B11 | C12: =C10*C11 | D12: =D10*D11 | E12: Terminal cash earnings proxy.
A13: Exit FCF multiple | B13: 15 | C13: 17 | D13: 19 | E13: Multiple on terminal adjusted FCF.
A14: Implied EV ($M) | B14: =B12*B13 | C14: =C12*C13 | D14: =D12*D13 | E14: Terminal adjusted FCF × exit multiple.
A15: Less: net debt adj. ($M) | B15: =Valuation!B10 | C15: =Valuation!B10 | D15: =Valuation!B10 | E15: Uses current net debt as a conservative claim stack proxy.
A16: Implied equity value ($M) | B16: =B14-B15 | C16: =C14-C15 | D16: =D14-D15 | E16: EV less net debt.
A17: Diluted shares (M) | B17: 64.2 | C17: 63.8 | D17: 63.2 | E17: Assumes mild dilution in bear/base and slight offset from retained cash in bull.
A18: Target price | B18: =B16/B17 | C18: =C16/C17 | D18: =D16/D17 | E18: Implied equity value per share.
A19: Upside vs. current | B19: =B18/$B$3-1 | C19: =C18/$B$3-1 | D19: =D18/$B$3-1 | E19: Price return versus $122.81.
A20: Scenario weight | B20: 0.25 | C20: 0.5 | D20: 0.25 | E20: Probabilities sum to 100%.
A21: Weighted value / share | B21: =B18*B20 | C21: =C18*C20 | D21: =D18*D20 | E21: Scenario target price × weight.
B22: =SUM(B21:D21) | E22: Total probability-weighted fair value per share.
B23: =B22/$B$3-1 | E23: Weighted upside from current price.

Sheet Actuals Source Audit
A1: Ryman Hospitality Properties (RHP) — Actuals / Source Audit
A2: Line item | B2: Period | C2: Model value | D2: Unit | E2: Primary source | F2: Secondary source | G2: Resolution / note | H2: Model cell
A3: Share price | B3: 2026-06-12 | C3: 122.81 | D3: USD/share | E3: https://stockanalysis.com/stocks/rhp/ | F3: research/RHP.md | G3: June 12 close used because model date is a Sunday. | H3: Valuation!B5
A4: Shares outstanding | B4: Current | C4: 62.77 | D4: M | E4: https://stockanalysis.com/stocks/rhp/statistics/ | F4: https://stockanalysis.com/stocks/rhp/ | G4: Statistics and overview match on 62.77M shares. | H4: Valuation!B6
A5: Market cap | B5: Current | C5: 7710 | D5: USD mm | E5: https://stockanalysis.com/stocks/rhp/statistics/ | F5: https://stockanalysis.com/stocks/rhp/ | G5: Rounded from $7.71B. | H5: Valuation!B7
A6: Enterprise value | B6: Current | C6: 11410 | D6: USD mm | E6: https://stockanalysis.com/stocks/rhp/statistics/ | F6: research/RHP.md | G6: Provider EV exceeds simple debt-minus-cash because of lease/NCI treatment. | H6: n/a
A7: Revenue | B7: TTM | C7: 2654 | D7: USD mm | E7: https://stockanalysis.com/stocks/rhp/financials/ | F7: research/RHP.md | G7: TTM through Mar. 31, 2026. | H7: Valuation!B29
A8: Revenue | B8: FY2025 | C8: 2577 | D8: USD mm | E8: https://stockanalysis.com/stocks/rhp/financials/ | F8: research/RHP.md | G8: Matches local research note. | H8: Valuation!C29
A9: Gross profit | B9: FY2025 | C9: 812.06 | D9: USD mm | E9: https://stockanalysis.com/stocks/rhp/financials/ | F9: n/a | G9: Derived standardized gross profit line from StockAnalysis. | H9: Valuation!C31
A10: Operating income | B10: FY2025 | C10: 487.01 | D10: USD mm | E10: https://stockanalysis.com/stocks/rhp/financials/ | F10: research/RHP.md | G10: Cross-checked to research note narrative. | H10: Valuation!C33
A11: EBITDA | B11: TTM | C11: 798.77 | D11: USD mm | E11: https://stockanalysis.com/stocks/rhp/financials/ | F11: https://stockanalysis.com/stocks/rhp/statistics/ | G11: Aligns with EV/EBITDA screen. | H11: Valuation!B35
A12: Net income | B12: FY2025 | C12: 247.31 | D12: USD mm | E12: https://stockanalysis.com/stocks/rhp/financials/ | F12: https://stockanalysis.com/stocks/rhp/financials/cash-flow-statement/ | G12: Income statement and cash flow statement line up. | H12: Valuation!C37
A13: Operating cash flow | B13: FY2025 | C13: 590.63 | D13: USD mm | E13: https://stockanalysis.com/stocks/rhp/financials/cash-flow-statement/ | F13: research/RHP.md | G13: Cash generation before capex and acquisitions. | H13: Valuation!C40
A14: Free cash flow | B14: FY2025 | C14: 232.39 | D14: USD mm | E14: https://stockanalysis.com/stocks/rhp/financials/cash-flow-statement/ | F14: research/RHP.md | G14: Headline FCF remains capex-sensitive for a resort REIT. | H14: Valuation!C42
... A22: 10Y Treasury | B22: 2026-06-11 | C22: 0.0445 | D22: percent | E22: https://fred.stlouisfed.org/series/DGS10 | F22: n/a | G22: Latest observation before model date was 4.45%. | H22: WACC!B4

Sheet Questions
A1: Ryman Hospitality Properties (RHP) — Underwriting Questions
A2: # | B2: Question | C2: Focus area
A3: 1 | B3: How much of current growth is same-store group pricing and spend, and how much is simply Desert Ridge acquisition math? | C3: Growth quality
A4: 2 | B4: Can Desert Ridge and Hill Country sustain per-share FFO accretion after financing costs and ongoing capex? | C4: Capital allocation
A5: 3 | B5: What is the true maintenance-capex requirement for the Gaylord and JW Marriott resort base? | C5: Owner earnings
A6: 4 | B6: How cyclical are net definite group room nights if corporate meeting budgets soften in 2027? | C6: Macro sensitivity
A7: 5 | B7: Is the Entertainment segment a strategic moat enhancer or a structurally lower-return complexity layer? | C7: Segment mix
A8: 6 | B8: How much refinancing risk sits inside the $4.1B debt stack if rates stay elevated for longer? | C8: Balance sheet
A9: 7 | B9: Does the 3.9% dividend remain comfortably covered through a softer convention cycle? | C9: Dividend safety
A10: 8 | B10: Will equity issuance remain part of the acquisition playbook, or can future deals be funded without share dilution? | C10: Per-share value
A11: 9 | B11: Do Marriott management and asset scarcity justify a premium multiple even if absolute revenue growth slows to mid-single digits? | C11: Multiple support
A12: 10 | B12: Are deferred revenue and booking indicators still confirming healthy future group demand, or merely reflecting price increases? | C12: Leading indicators

Sheet Sources
A1: Ryman Hospitality Properties (RHP) — Sources
A2: Source | B2: Type | C2: Date / as-of | D2: Usage | E2: URL / note
A3: StockAnalysis overview | B3: Market data | C3: 2026-06-14 | D3: Price, beta, shares, company overview | E3: https://stockanalysis.com/stocks/rhp/
A4: StockAnalysis income statement | B4: Financial statements | C4: 2026-06-14 | D4: Revenue, margins, EBITDA, EPS | E4: https://stockanalysis.com/stocks/rhp/financials/
A5: StockAnalysis balance sheet | B5: Financial statements | C5: 2026-06-14 | D5: Cash, debt, assets, equity | E5: https://stockanalysis.com/stocks/rhp/financials/balance-sheet/
A6: StockAnalysis cash flow statement | B6: Financial statements | C6: 2026-06-14 | D6: OCF, capex, FCF | E6: https://stockanalysis.com/stocks/rhp/financials/cash-flow-statement/
A7: StockAnalysis statistics | B7: Valuation | C7: 2026-06-14 | D7: Market cap, EV, P/FFO, EV/EBITDA, leverage ratios | E7: https://stockanalysis.com/stocks/rhp/statistics/
A8: StockAnalysis forecast | B8: Consensus | C8: 2026-06-14 | D8: FY2026 revenue, FFO/share, price targets, ratings | E8: https://stockanalysis.com/stocks/rhp/forecast/
A9: FRED DGS10 | B9: Rate source | C9: 2026-06-11 obs / 2026-06-12 update | D9: Risk-free rate for WACC | E9: https://fred.stlouisfed.org/series/DGS10
A10: Local research note | B10: Repo-local research | C10: 2026-06-14 | D10: Cross-check on qualitative framing, debt stack, and questions | E10: research/RHP.md
A11: Ryman Hospitality website | B11: Company profile | C11: 2026-06-14 | D11: Asset footprint and business description | E11: https://www.rymanhp.com
